{
	"map_events": [],
	"map_npcs": [
		{
			"aggro_range": 3,
			"battle_ai": 0,
			"coin": 0,
			"flag_given": "",
			"flag_required": "",
			"flag_kill": "",
			"remove_on_finish": true,
			"is_catchable": false,
			"items": [],
			"name": "Wandering Trainer",
			"npc_id": "494143645148270972Everchange Cave - Floor 1",
			"pre_combat_dialogue": "Hey, so I might be a little lost.",
			"post_combat_dialogue": "*The trainer suddenly vanishes...*",
			"sprite": 0,
			"sprite_combat": "",
			"sprite_dialog": "",
			"dialogue_portrait": "",
			"sprite_id": "c00_002",
			"stance_list": [
				0
			],
			"team": [
				{
					"id": 24,
					"level": 24,
					"nickname": "Tisparc",
					"ability": 25,
					"moveset": [
						1,
						61,
						24,
						4
					],
					"hp_iv": 13,
					"atk_iv": 15,
					"def_iv": 13,
					"spd_iv": 18,
					"slot_enabled": true,
					"item": -1
				},
				{
					"id": 94,
					"level": 24,
					"nickname": "Silentoad",
					"ability": 73,
					"moveset": [
						95,
						62,
						98,
						119
					],
					"hp_iv": 16,
					"atk_iv": 20,
					"def_iv": 18,
					"spd_iv": 15,
					"slot_enabled": true,
					"item": -1
				},
				{
					"id": 52,
					"level": 23,
					"nickname": "Vrumbox",
					"ability": 29,
					"moveset": [
						1,
						62,
						59,
						71
					],
					"hp_iv": 15,
					"atk_iv": 19,
					"def_iv": 10,
					"spd_iv": 18,
					"slot_enabled": true,
					"item": -1
				}
			],
			"x": 16,
			"y": 29
		},
		{
			"aggro_range": 3,
			"battle_ai": 0,
			"coin": 0,
			"flag_given": "",
			"flag_required": "",
			"flag_kill": "",
			"remove_on_finish": true,
			"is_catchable": false,
			"items": [],
			"name": "Wandering Trainer",
			"npc_id": "006914162111803972Everchange Cave - Floor 1",
			"pre_combat_dialogue": "If not supposed to eat battery, why battery taste good?",
			"post_combat_dialogue": "*The trainer suddenly vanishes...*",
			"sprite": 0,
			"sprite_combat": "",
			"sprite_dialog": "",
			"dialogue_portrait": "",
			"sprite_id": "c00_005",
			"stance_list": [
				0
			],
			"team": [
				{
					"id": 68,
					"level": 27,
					"nickname": "Speculidae",
					"ability": 34,
					"moveset": [
						1,
						94,
						87,
						106
					],
					"hp_iv": 17,
					"atk_iv": 11,
					"def_iv": 19,
					"spd_iv": 10,
					"slot_enabled": true,
					"item": -1
				}
			],
			"x": 23,
			"y": 43
		},
		{
			"aggro_range": 3,
			"battle_ai": 0,
			"coin": 0,
			"flag_given": "",
			"flag_required": "",
			"flag_kill": "",
			"remove_on_finish": true,
			"is_catchable": false,
			"items": [],
			"name": "Wandering Trainer",
			"npc_id": "575870440273591150Everchange Cave - Floor 1",
			"pre_combat_dialogue": "This isn't even my final form!",
			"post_combat_dialogue": "*The trainer suddenly vanishes...*",
			"sprite": 0,
			"sprite_combat": "",
			"sprite_dialog": "",
			"dialogue_portrait": "",
			"sprite_id": "c00_002",
			"stance_list": [
				0
			],
			"team": [
				{
					"id": 66,
					"level": 24,
					"nickname": "Grubbit",
					"ability": 31,
					"moveset": [
						85,
						87,
						80,
						11
					],
					"hp_iv": 15,
					"atk_iv": 20,
					"def_iv": 11,
					"spd_iv": 10,
					"slot_enabled": true,
					"item": -1
				},
				{
					"id": 40,
					"level": 25,
					"nickname": "Codet",
					"ability": 17,
					"moveset": [
						1,
						69,
						44,
						82
					],
					"hp_iv": 17,
					"atk_iv": 11,
					"def_iv": 17,
					"spd_iv": 15,
					"slot_enabled": true,
					"item": -1
				}
			],
			"x": 41,
			"y": 36
		},
		{
			"aggro_range": 3,
			"battle_ai": 0,
			"coin": 0,
			"flag_given": "",
			"flag_required": "",
			"flag_kill": "",
			"remove_on_finish": true,
			"is_catchable": false,
			"items": [],
			"name": "Wandering Trainer",
			"npc_id": "903645567731163906Everchange Cave - Floor 1",
			"pre_combat_dialogue": "I have never known defeat!",
			"post_combat_dialogue": "*The trainer suddenly vanishes...*",
			"sprite": 0,
			"sprite_combat": "",
			"sprite_dialog": "",
			"dialogue_portrait": "",
			"sprite_id": "c00_005",
			"stance_list": [
				0
			],
			"team": [
				{
					"id": 115,
					"level": 24,
					"nickname": "Parmanyan",
					"ability": 8,
					"moveset": [
						1,
						61,
						23,
						86
					],
					"hp_iv": 17,
					"atk_iv": 14,
					"def_iv": 19,
					"spd_iv": 20,
					"slot_enabled": true,
					"item": -1
				},
				{
					"id": 23,
					"level": 24,
					"nickname": "Meduslime",
					"ability": 22,
					"moveset": [
						1,
						60,
						29,
						23
					],
					"hp_iv": 13,
					"atk_iv": 10,
					"def_iv": 18,
					"spd_iv": 14,
					"slot_enabled": true,
					"item": -1
				},
				{
					"id": 35,
					"level": 24,
					"nickname": "Cromet",
					"ability": 14,
					"moveset": [
						1,
						3,
						64,
						11
					],
					"hp_iv": 10,
					"atk_iv": 13,
					"def_iv": 12,
					"spd_iv": 16,
					"slot_enabled": true,
					"item": -1
				}
			],
			"x": 37,
			"y": 31
		},
		{
			"aggro_range": 3,
			"battle_ai": 0,
			"coin": 0,
			"flag_given": "",
			"flag_required": "",
			"flag_kill": "",
			"remove_on_finish": true,
			"is_catchable": false,
			"items": [],
			"name": "Wandering Trainer",
			"npc_id": "098451817055547153Everchange Cave - Floor 1",
			"pre_combat_dialogue": "Martial-type? No, I don't think that's a thing.",
			"post_combat_dialogue": "*The trainer suddenly vanishes...*",
			"sprite": 0,
			"sprite_combat": "",
			"sprite_dialog": "",
			"dialogue_portrait": "",
			"sprite_id": "c00_001",
			"stance_list": [
				0
			],
			"team": [
				{
					"id": 99,
					"level": 26,
					"nickname": "Shieldome",
					"ability": 66,
					"moveset": [
						3,
						85,
						100,
						37
					],
					"hp_iv": 10,
					"atk_iv": 12,
					"def_iv": 15,
					"spd_iv": 11,
					"slot_enabled": true,
					"item": -1
				}
			],
			"x": 16,
			"y": 14
		},
		{
			"aggro_range": 0,
			"battle_ai": 0,
			"coin": 0,
			"flag_given": "",
			"flag_required": "",
			"flag_kill": "",
			"remove_on_finish": true,
			"is_catchable": false,
			"items": [
				{
					"count": 1,
					"id": 16
				}
			],
			"name": "Chest",
			"npc_id": "660261669954081548Everchange Cave - Floor 1",
			"pre_combat_dialogue": "You opened the chest...",
			"post_combat_dialogue": "",
			"sprite": 0,
			"sprite_combat": "",
			"sprite_dialog": "",
			"dialogue_portrait": "",
			"sprite_id": "c00_013",
			"stance_list": [
				0
			],
			"team": [],
			"x": 27,
			"y": 20
		},
		{
			"aggro_range": 0,
			"battle_ai": 0,
			"coin": 0,
			"flag_given": "",
			"flag_required": "",
			"flag_kill": "",
			"remove_on_finish": true,
			"is_catchable": false,
			"items": [
				{
					"count": 2,
					"id": 12
				},
				{
					"count": 3,
					"id": 3
				}
			],
			"name": "Chest",
			"npc_id": "281413723364017211Everchange Cave - Floor 1",
			"pre_combat_dialogue": "You opened the chest...",
			"post_combat_dialogue": "",
			"sprite": 0,
			"sprite_combat": "",
			"sprite_dialog": "",
			"dialogue_portrait": "",
			"sprite_id": "c00_013",
			"stance_list": [
				0
			],
			"team": [],
			"x": 24,
			"y": 26
		}
	],
	"map_savepoints": [],
	"map_shops": [],
	"map_spawn_zones": [
		{
			"x": 39,
			"y": 30,
			"height": 4,
			"width": 2,
			"spawn_slots": [
				{
					"min_level": 22,
					"max_level": 26,
					"ooch_id": 20
				},
				{
					"min_level": 22,
					"max_level": 26,
					"ooch_id": 80
				},
				{
					"min_level": 22,
					"max_level": 26,
					"ooch_id": 22
				}
			]
		},
		{
			"x": 31,
			"y": 35,
			"height": 4,
			"width": 2,
			"spawn_slots": [
				{
					"min_level": 22,
					"max_level": 26,
					"ooch_id": 23
				},
				{
					"min_level": 22,
					"max_level": 26,
					"ooch_id": 11
				},
				{
					"min_level": 22,
					"max_level": 26,
					"ooch_id": 78
				}
			]
		},
		{
			"x": 34,
			"y": 15,
			"height": 2,
			"width": 4,
			"spawn_slots": [
				{
					"min_level": 22,
					"max_level": 26,
					"ooch_id": 11
				},
				{
					"min_level": 22,
					"max_level": 26,
					"ooch_id": 19
				},
				{
					"min_level": 22,
					"max_level": 26,
					"ooch_id": 50
				}
			]
		},
		{
			"x": 35,
			"y": 11,
			"height": 4,
			"width": 4,
			"spawn_slots": [
				{
					"min_level": 22,
					"max_level": 26,
					"ooch_id": 14
				},
				{
					"min_level": 22,
					"max_level": 26,
					"ooch_id": 17
				},
				{
					"min_level": 22,
					"max_level": 26,
					"ooch_id": 101
				}
			]
		},
		{
			"x": 13,
			"y": 27,
			"height": 4,
			"width": 4,
			"spawn_slots": [
				{
					"min_level": 22,
					"max_level": 26,
					"ooch_id": 93
				},
				{
					"min_level": 22,
					"max_level": 26,
					"ooch_id": 101
				},
				{
					"min_level": 22,
					"max_level": 26,
					"ooch_id": 32
				}
			]
		},
		{
			"x": 27,
			"y": 37,
			"height": 4,
			"width": 2,
			"spawn_slots": [
				{
					"min_level": 22,
					"max_level": 26,
					"ooch_id": 46
				},
				{
					"min_level": 22,
					"max_level": 26,
					"ooch_id": 109
				},
				{
					"min_level": 22,
					"max_level": 26,
					"ooch_id": 127
				}
			]
		},
		{
			"x": 23,
			"y": 22,
			"height": 2,
			"width": 4,
			"spawn_slots": [
				{
					"min_level": 22,
					"max_level": 26,
					"ooch_id": 40
				},
				{
					"min_level": 22,
					"max_level": 26,
					"ooch_id": 23
				},
				{
					"min_level": 22,
					"max_level": 26,
					"ooch_id": 55
				}
			]
		},
		{
			"x": 15,
			"y": 36,
			"height": 4,
			"width": 2,
			"spawn_slots": [
				{
					"min_level": 22,
					"max_level": 26,
					"ooch_id": 29
				},
				{
					"min_level": 22,
					"max_level": 26,
					"ooch_id": 94
				},
				{
					"min_level": 22,
					"max_level": 26,
					"ooch_id": 15
				}
			]
		},
		{
			"x": 23,
			"y": 38,
			"height": 4,
			"width": 4,
			"spawn_slots": [
				{
					"min_level": 22,
					"max_level": 26,
					"ooch_id": 17
				},
				{
					"min_level": 22,
					"max_level": 26,
					"ooch_id": 90
				},
				{
					"min_level": 22,
					"max_level": 26,
					"ooch_id": 60
				}
			]
		}
	],
	"map_transitions": [
		{
			"connect_map": "everchange_cave_-_floor_2",
			"connect_x": -1,
			"connect_y": -1,
			"x": 16,
			"y": 38
		}
	],
	"map_tiles": [
		[
			"t01_006",
			"t01_006",
			"t01_006",
			"t01_006",
			"t01_006",
			"t01_006",
			"t01_006",
			"t01_006",
			"t01_006",
			"t01_006",
			"t01_006",
			"t01_006",
			"t01_006",
			"t01_006",
			"t01_006",
			"t01_006",
			"t01_006",
			"t01_006",
			"t01_006",
			"t01_006",
			"t01_006",
			"t01_006",
			"t01_006",
			"t01_006",
			"t01_006",
			"t01_006",
			"t01_006",
			"t01_006",
			"t01_006",
			"t01_006",
			"t01_006",
			"t01_006",
			"t01_006",
			"t01_006",
			"t01_006",
			"t01_006",
			"t01_006",
			"t01_006",
			"t01_006",
			"t01_006",
			"t01_006",
			"t01_006",
			"t01_006",
			"t01_006",
			"t01_006",
			"t01_006",
			"t01_006",
			"t01_006"
		],
		[
			"t01_006",
			"t01_006",
			"t01_006",
			"t01_006",
			"t01_006",
			"t01_006",
			"t01_006",
			"t01_006",
			"t01_006",
			"t01_006",
			"t01_006",
			"t01_006",
			"t01_006",
			"t01_006",
			"t01_006",
			"t01_006",
			"t01_006",
			"t01_006",
			"t01_006",
			"t01_006",
			"t01_006",
			"t01_006",
			"t01_006",
			"t01_006",
			"t01_006",
			"t01_006",
			"t01_006",
			"t01_006",
			"t01_006",
			"t01_006",
			"t01_006",
			"t01_006",
			"t01_006",
			"t01_006",
			"t01_006",
			"t01_006",
			"t01_006",
			"t01_006",
			"t01_006",
			"t01_006",
			"t01_006",
			"t01_006",
			"t01_006",
			"t01_006",
			"t01_006",
			"t01_006",
			"t01_006",
			"t01_006"
		],
		[
			"t01_006",
			"t01_006",
			"t01_006",
			"t01_006",
			"t01_006",
			"t01_006",
			"t01_006",
			"t01_006",
			"t01_006",
			"t01_006",
			"t01_006",
			"t01_006",
			"t01_006",
			"t01_006",
			"t01_006",
			"t01_006",
			"t01_006",
			"t01_006",
			"t01_006",
			"t01_006",
			"t01_006",
			"t01_006",
			"t01_006",
			"t01_006",
			"t01_006",
			"t01_006",
			"t01_006",
			"t01_006",
			"t01_006",
			"t01_006",
			"t01_006",
			"t01_006",
			"t01_006",
			"t01_006",
			"t01_006",
			"t01_006",
			"t01_006",
			"t01_006",
			"t01_006",
			"t01_006",
			"t01_006",
			"t01_006",
			"t01_006",
			"t01_006",
			"t01_006",
			"t01_006",
			"t01_006",
			"t01_006"
		],
		[
			"t01_006",
			"t01_006",
			"t01_006",
			"t01_006",
			"t01_006",
			"t01_006",
			"t01_006",
			"t01_006",
			"t01_006",
			"t01_006",
			"t01_006",
			"t01_006",
			"t01_006",
			"t01_006",
			"t01_006",
			"t01_006",
			"t01_006",
			"t01_006",
			"t01_006",
			"t01_006",
			"t01_006",
			"t01_006",
			"t01_006",
			"t01_006",
			"t01_006",
			"t01_006",
			"t01_006",
			"t01_006",
			"t01_006",
			"t01_006",
			"t01_006",
			"t01_006",
			"t01_006",
			"t01_006",
			"t01_006",
			"t01_006",
			"t01_006",
			"t01_006",
			"t01_006",
			"t01_006",
			"t01_006",
			"t01_006",
			"t01_006",
			"t01_006",
			"t01_006",
			"t01_006",
			"t01_006",
			"t01_006"
		],
		[
			"t01_006",
			"t01_006",
			"t01_006",
			"t01_006",
			"t01_006",
			"t01_006",
			"t01_006",
			"t01_006",
			"t01_006",
			"t01_006",
			"t01_006",
			"t01_006",
			"t01_006",
			"t01_006",
			"t01_006",
			"t01_006",
			"t01_006",
			"t01_006",
			"t01_006",
			"t01_006",
			"t01_006",
			"t01_006",
			"t01_006",
			"t01_006",
			"t01_006",
			"t01_006",
			"t01_006",
			"t01_006",
			"t01_006",
			"t01_006",
			"t01_006",
			"t01_006",
			"t01_006",
			"t01_006",
			"t01_006",
			"t01_006",
			"t01_006",
			"t01_006",
			"t01_006",
			"t01_006",
			"t01_006",
			"t01_006",
			"t01_006",
			"t01_006",
			"t01_006",
			"t01_006",
			"t01_006",
			"t01_006"
		],
		[
			"t01_006",
			"t01_006",
			"t01_006",
			"t01_006",
			"t01_006",
			"t01_006",
			"t01_006",
			"t01_006",
			"t01_006",
			"t01_006",
			"t01_006",
			"t01_006",
			"t01_006",
			"t01_006",
			"t01_006",
			"t01_006",
			"t01_006",
			"t01_006",
			"t01_006",
			"t01_006",
			"t01_006",
			"t01_006",
			"t01_006",
			"t01_006",
			"t01_006",
			"t01_006",
			"t01_006",
			"t01_006",
			"t01_006",
			"t01_006",
			"t01_006",
			"t01_006",
			"t01_006",
			"t01_006",
			"t01_006",
			"t01_006",
			"t01_006",
			"t01_006",
			"t01_006",
			"t01_006",
			"t01_006",
			"t01_006",
			"t01_006",
			"t01_006",
			"t01_006",
			"t01_006",
			"t01_006",
			"t01_006"
		],
		[
			"t01_006",
			"t01_006",
			"t01_006",
			"t01_006",
			"t01_006",
			"t01_006",
			"t01_006",
			"t01_006",
			"t01_006",
			"t01_006",
			"t01_006",
			"t01_006",
			"t01_006",
			"t01_006",
			"t01_006",
			"t01_006",
			"t01_006",
			"t01_006",
			"t01_006",
			"t01_006",
			"t01_006",
			"t01_006",
			"t01_006",
			"t01_006",
			"t01_006",
			"t01_006",
			"t01_006",
			"t01_006",
			"t01_006",
			"t01_006",
			"t01_006",
			"t01_006",
			"t01_006",
			"t01_006",
			"t01_006",
			"t01_006",
			"t01_006",
			"t01_006",
			"t01_006",
			"t01_006",
			"t01_006",
			"t01_006",
			"t01_006",
			"t01_006",
			"t01_006",
			"t01_006",
			"t01_006",
			"t01_006"
		],
		[
			"t01_006",
			"t01_006",
			"t01_006",
			"t01_006",
			"t01_006",
			"t01_006",
			"t01_006",
			"t01_006",
			"t01_006",
			"t01_006",
			"t01_006",
			"t01_006",
			"t01_006",
			"t01_006",
			"t01_006",
			"t01_006",
			"t01_006",
			"t01_006",
			"t01_006",
			"t01_006",
			"t01_006",
			"t01_006",
			"t01_006",
			"t01_006",
			"t01_006",
			"t01_006",
			"t01_006",
			"t01_006",
			"t01_006",
			"t01_006",
			"t01_006",
			"t01_006",
			"t01_006",
			"t01_006",
			"t01_006",
			"t01_006",
			"t01_006",
			"t01_006",
			"t01_006",
			"t01_006",
			"t01_006",
			"t01_006",
			"t01_006",
			"t01_006",
			"t01_006",
			"t01_006",
			"t01_006",
			"t01_006"
		],
		[
			"t01_006",
			"t01_006",
			"t01_006",
			"t01_006",
			"t01_006",
			"t01_006",
			"t01_006",
			"t01_006",
			"t01_006",
			"t01_006",
			"t01_006",
			"t01_006",
			"t01_006",
			"t01_006",
			"t01_006",
			"t01_006",
			"t01_006",
			"t01_006",
			"t01_006",
			"t01_006",
			"t01_006",
			"t01_006",
			"t01_006",
			"t01_006",
			"t01_006",
			"t01_006",
			"t01_006",
			"t01_006",
			"t01_006",
			"t01_006",
			"t01_006",
			"t01_006",
			"t01_006",
			"t01_006",
			"t01_006",
			"t01_006",
			"t01_006",
			"t01_006",
			"t01_006",
			"t01_006",
			"t01_006",
			"t01_006",
			"t01_006",
			"t01_006",
			"t01_006",
			"t01_006",
			"t01_006",
			"t01_006"
		],
		[
			"t01_006",
			"t01_006",
			"t01_006",
			"t01_006",
			"t01_006",
			"t01_006",
			"t01_006",
			"t01_006",
			"t01_006",
			"t01_006",
			"t01_006",
			"t01_006",
			"t01_006",
			"t01_006",
			"t01_006",
			"t01_006",
			"t01_006",
			"t01_006",
			"t01_006",
			"t01_006",
			"t01_006",
			"t01_006",
			"t01_006",
			"t01_006",
			"t01_006",
			"t01_006",
			"t01_006",
			"t01_006",
			"t01_006",
			"t01_006",
			"t01_006",
			"t01_006",
			"t01_006",
			"t01_006",
			"t01_006",
			"t01_006",
			"t01_006",
			"t01_006",
			"t01_006",
			"t01_006",
			"t01_006",
			"t01_006",
			"t01_006",
			"t01_006",
			"t01_006",
			"t01_006",
			"t01_006",
			"t01_006"
		],
		[
			"t01_006",
			"t01_006",
			"t01_006",
			"t01_006",
			"t01_006",
			"t01_006",
			"t01_006",
			"t01_006",
			"t01_006",
			"t01_006",
			"t01_006",
			"t01_006",
			"t01_006",
			"t01_006",
			"t01_006",
			"t01_006",
			"t01_006",
			"t01_006",
			"t01_006",
			"t01_006",
			"t01_006",
			"t01_006",
			"t01_006",
			"t01_006",
			"t01_006",
			"t01_006",
			"t01_006",
			"t01_006",
			"t01_006",
			"t01_006",
			"t01_006",
			"t01_006",
			"t01_006",
			"t01_006",
			"t01_006",
			"t01_006",
			"t01_006",
			"t01_006",
			"t01_006",
			"t01_006",
			"t01_006",
			"t01_006",
			"t01_006",
			"t01_006",
			"t01_006",
			"t01_006",
			"t01_006",
			"t01_006"
		],
		[
			"t01_006",
			"t01_006",
			"t01_006",
			"t01_006",
			"t01_006",
			"t01_006",
			"t01_006",
			"t01_006",
			"t01_006",
			"t01_006",
			"t01_006",
			"t01_006",
			"t01_006",
			"t01_006",
			"t01_006",
			"t01_006",
			"t01_006",
			"t01_006",
			"t01_006",
			"t01_006",
			"t01_006",
			"t01_006",
			"t01_006",
			"t01_006",
			"t01_006",
			"t01_006",
			"t01_006",
			"t01_006",
			"t01_006",
			"t01_006",
			"t01_006",
			"t01_006",
			"t01_006",
			"t01_006",
			"t01_006",
			"t01_006",
			"t01_006",
			"t01_006",
			"t01_006",
			"t01_006",
			"t01_006",
			"t01_006",
			"t01_006",
			"t01_006",
			"t01_006",
			"t01_006",
			"t01_006",
			"t01_006"
		],
		[
			"t01_006",
			"t01_006",
			"t01_006",
			"t01_006",
			"t01_006",
			"t01_006",
			"t01_006",
			"t01_006",
			"t01_006",
			"t01_006",
			"t01_006",
			"t01_006",
			"t01_006",
			"t01_006",
			"t01_006",
			"t01_006",
			"t01_006",
			"t01_006",
			"t01_006",
			"t01_006",
			"t01_006",
			"t01_006",
			"t01_006",
			"t01_006",
			"t01_006",
			"t01_006",
			"t01_006",
			"t01_006",
			"t01_006",
			"t01_006",
			"t01_006",
			"t01_006",
			"t01_006",
			"t01_006",
			"t01_006",
			"t01_006",
			"t01_006",
			"t01_006",
			"t01_006",
			"t01_006",
			"t01_006",
			"t01_006",
			"t01_006",
			"t01_006",
			"t01_006",
			"t01_006",
			"t01_006",
			"t01_006"
		],
		[
			"t01_006",
			"t01_006",
			"t01_006",
			"t01_006",
			"t01_006",
			"t01_006",
			"t01_006",
			"t01_006",
			"t01_006",
			"t01_006",
			"t01_006",
			"t01_006",
			"t01_006",
			"t01_006",
			"t01_006",
			"t01_006",
			"t01_006",
			"t01_006",
			"t01_006",
			"t01_006",
			"t01_006",
			"t01_006",
			"t01_006",
			"t01_006",
			"t01_006",
			"t01_006",
			"t01_006",
			"t01_006",
			"t01_006",
			"t01_006",
			"t01_006",
			"t01_006",
			"t01_006",
			"t01_006",
			"t01_006",
			"t01_006",
			"t01_006",
			"t01_006",
			"t01_006",
			"t01_006",
			"t01_006",
			"t01_006",
			"t01_006",
			"t01_006",
			"t01_006",
			"t01_006",
			"t01_006",
			"t01_006"
		],
		[
			"t01_006",
			"t01_006",
			"t01_006",
			"t01_006",
			"t01_006",
			"t01_006",
			"t01_006",
			"t01_006",
			"t01_006",
			"t01_006",
			"t01_006",
			"t01_006",
			"t01_006",
			"t01_003",
			"t01_000",
			"t01_006",
			"t01_006",
			"t01_006",
			"t01_006",
			"t01_006",
			"t01_006",
			"t01_006",
			"t01_006",
			"t01_006",
			"t01_006",
			"t01_006",
			"t01_006",
			"t01_006",
			"t01_003",
			"t01_002",
			"t01_006",
			"t01_006",
			"t01_006",
			"t01_006",
			"t01_006",
			"t01_006",
			"t01_006",
			"t01_003",
			"t01_000",
			"t01_006",
			"t01_006",
			"t01_006",
			"t01_006",
			"t01_006",
			"t01_006",
			"t01_006",
			"t01_006",
			"t01_006"
		],
		[
			"t01_006",
			"t01_006",
			"t01_006",
			"t01_006",
			"t01_006",
			"t01_006",
			"t01_006",
			"t01_006",
			"t01_006",
			"t01_006",
			"t01_006",
			"t01_006",
			"t01_003",
			"t01_000",
			"t01_000",
			"t01_000",
			"t01_000",
			"t01_000",
			"t01_000",
			"t01_000",
			"t01_000",
			"t01_000",
			"t01_000",
			"t01_000",
			"t01_000",
			"t01_001",
			"t01_000",
			"t01_002",
			"t01_002",
			"t01_002",
			"t01_002",
			"t01_002",
			"t01_000",
			"t01_000",
			"t01_000",
			"t01_000",
			"t01_002",
			"t01_001",
			"t01_002",
			"t01_002",
			"t01_002",
			"t01_000",
			"t01_006",
			"t01_006",
			"t01_006",
			"t01_006",
			"t01_006",
			"t01_006"
		],
		[
			"t01_006",
			"t01_006",
			"t01_006",
			"t01_006",
			"t01_006",
			"t01_006",
			"t01_006",
			"t01_006",
			"t01_006",
			"t01_006",
			"t01_006",
			"t01_003",
			"t01_000",
			"t01_000",
			"t01_000",
			"t01_000",
			"t01_000",
			"t01_000",
			"t01_000",
			"t01_000",
			"t01_000",
			"t01_000",
			"t01_001",
			"t01_000",
			"t01_000",
			"t01_000",
			"t01_000",
			"t01_002",
			"t01_002",
			"t01_000",
			"t01_002",
			"t01_002",
			"t01_000",
			"t01_000",
			"t01_000",
			"t01_000",
			"t01_002",
			"t01_002",
			"t00_012",
			"t01_002",
			"t01_002",
			"t01_000",
			"t01_000",
			"t01_006",
			"t01_006",
			"t01_006",
			"t01_006",
			"t01_006"
		],
		[
			"t01_006",
			"t01_006",
			"t01_006",
			"t01_006",
			"t01_006",
			"t01_006",
			"t01_006",
			"t01_006",
			"t01_006",
			"t01_006",
			"t01_006",
			"t01_006",
			"t01_003",
			"t01_000",
			"t01_000",
			"t01_000",
			"t01_000",
			"t01_000",
			"t01_000",
			"t01_000",
			"t01_000",
			"t01_000",
			"t01_000",
			"t01_000",
			"t01_000",
			"t01_000",
			"t01_000",
			"t01_002",
			"t01_002",
			"t01_002",
			"t01_002",
			"t01_002",
			"t01_000",
			"t01_000",
			"t01_001",
			"t01_000",
			"t01_002",
			"t01_001",
			"t01_002",
			"t01_002",
			"t01_002",
			"t01_000",
			"t01_000",
			"t01_006",
			"t01_006",
			"t01_006",
			"t01_006",
			"t01_006"
		],
		[
			"t01_006",
			"t01_006",
			"t01_006",
			"t01_006",
			"t01_006",
			"t01_006",
			"t01_006",
			"t01_006",
			"t01_006",
			"t01_006",
			"t01_006",
			"t01_006",
			"t01_006",
			"t01_003",
			"t01_001",
			"t01_006",
			"t01_006",
			"t01_006",
			"t01_006",
			"t01_006",
			"t01_006",
			"t01_006",
			"t01_006",
			"t01_006",
			"t01_006",
			"t01_006",
			"t01_006",
			"t01_006",
			"t01_003",
			"t01_001",
			"t01_006",
			"t01_006",
			"t01_006",
			"t01_006",
			"t01_006",
			"t01_006",
			"t01_006",
			"t01_003",
			"t01_000",
			"t01_000",
			"t01_000",
			"t01_000",
			"t01_000",
			"t01_000",
			"t01_006",
			"t01_006",
			"t01_006",
			"t01_006"
		],
		[
			"t01_006",
			"t01_006",
			"t01_006",
			"t01_006",
			"t01_006",
			"t01_006",
			"t01_006",
			"t01_006",
			"t01_006",
			"t01_006",
			"t01_006",
			"t01_006",
			"t01_006",
			"t01_006",
			"t01_006",
			"t01_006",
			"t01_006",
			"t01_006",
			"t01_006",
			"t01_006",
			"t01_006",
			"t01_006",
			"t01_006",
			"t01_006",
			"t01_006",
			"t01_006",
			"t01_006",
			"t01_006",
			"t01_006",
			"t01_006",
			"t01_006",
			"t01_006",
			"t01_006",
			"t01_006",
			"t01_006",
			"t01_006",
			"t01_006",
			"t01_006",
			"t01_006",
			"t01_003",
			"t01_000",
			"t01_000",
			"t01_000",
			"t01_000",
			"t01_006",
			"t01_006",
			"t01_006",
			"t01_006"
		],
		[
			"t01_006",
			"t01_006",
			"t01_006",
			"t01_006",
			"t01_006",
			"t01_006",
			"t01_006",
			"t01_006",
			"t01_006",
			"t01_006",
			"t01_006",
			"t01_006",
			"t01_006",
			"t01_006",
			"t01_006",
			"t01_006",
			"t01_006",
			"t01_006",
			"t01_006",
			"t01_006",
			"t01_006",
			"t01_006",
			"t01_006",
			"t01_006",
			"t01_006",
			"t01_006",
			"t01_006",
			"t01_006",
			"t01_006",
			"t01_006",
			"t01_006",
			"t01_006",
			"t01_006",
			"t01_006",
			"t01_006",
			"t01_006",
			"t01_006",
			"t01_006",
			"t01_006",
			"t01_003",
			"t01_000",
			"t01_000",
			"t01_000",
			"t01_000",
			"t01_006",
			"t01_006",
			"t01_006",
			"t01_006"
		],
		[
			"t01_006",
			"t01_006",
			"t01_006",
			"t01_006",
			"t01_006",
			"t01_006",
			"t01_006",
			"t01_006",
			"t01_006",
			"t01_006",
			"t01_006",
			"t01_006",
			"t01_006",
			"t01_006",
			"t01_006",
			"t01_006",
			"t01_006",
			"t01_006",
			"t01_006",
			"t01_006",
			"t01_006",
			"t01_006",
			"t01_006",
			"t01_006",
			"t01_006",
			"t01_006",
			"t01_006",
			"t01_006",
			"t01_006",
			"t01_006",
			"t01_006",
			"t01_006",
			"t01_006",
			"t01_006",
			"t01_006",
			"t01_006",
			"t01_006",
			"t01_006",
			"t01_006",
			"t01_006",
			"t01_003",
			"t01_000",
			"t01_000",
			"t01_000",
			"t01_006",
			"t01_006",
			"t01_006",
			"t01_006"
		],
		[
			"t01_006",
			"t01_006",
			"t01_006",
			"t01_006",
			"t01_006",
			"t01_006",
			"t01_006",
			"t01_006",
			"t01_006",
			"t01_006",
			"t01_006",
			"t01_006",
			"t01_006",
			"t01_006",
			"t01_006",
			"t01_006",
			"t01_006",
			"t01_006",
			"t01_006",
			"t01_006",
			"t01_006",
			"t01_006",
			"t01_006",
			"t01_006",
			"t01_006",
			"t01_006",
			"t01_006",
			"t01_006",
			"t01_006",
			"t01_006",
			"t01_006",
			"t01_006",
			"t01_006",
			"t01_006",
			"t01_006",
			"t01_006",
			"t01_006",
			"t01_006",
			"t01_006",
			"t01_003",
			"t01_000",
			"t01_000",
			"t01_000",
			"t01_000",
			"t01_000",
			"t01_006",
			"t01_006",
			"t01_006"
		],
		[
			"t01_006",
			"t01_006",
			"t01_006",
			"t01_006",
			"t01_006",
			"t01_006",
			"t01_006",
			"t01_006",
			"t01_006",
			"t01_006",
			"t01_006",
			"t01_006",
			"t01_006",
			"t01_006",
			"t01_006",
			"t01_006",
			"t01_006",
			"t01_006",
			"t01_006",
			"t01_006",
			"t01_006",
			"t01_006",
			"t01_006",
			"t01_003",
			"t01_002",
			"t01_001",
			"t01_000",
			"t01_000",
			"t01_006",
			"t01_006",
			"t01_006",
			"t01_006",
			"t01_006",
			"t01_006",
			"t01_006",
			"t01_006",
			"t01_006",
			"t01_006",
			"t01_003",
			"t01_002",
			"t01_002",
			"t01_002",
			"t01_002",
			"t01_000",
			"t01_000",
			"t01_006",
			"t01_006",
			"t01_006"
		],
		[
			"t01_006",
			"t01_006",
			"t01_006",
			"t01_006",
			"t01_006",
			"t01_006",
			"t01_006",
			"t01_006",
			"t01_006",
			"t01_006",
			"t01_006",
			"t01_006",
			"t01_006",
			"t01_006",
			"t01_006",
			"t01_006",
			"t01_006",
			"t01_006",
			"t01_006",
			"t01_006",
			"t01_006",
			"t01_006",
			"t01_003",
			"t01_002",
			"t01_002",
			"t01_000",
			"t01_000",
			"t01_000",
			"t01_006",
			"t01_006",
			"t01_006",
			"t01_006",
			"t01_006",
			"t01_006",
			"t01_006",
			"t01_006",
			"t01_003",
			"t01_000",
			"t01_002",
			"t01_002",
			"t01_002",
			"t01_002",
			"t01_002",
			"t01_000",
			"t01_000",
			"t01_006",
			"t01_006",
			"t01_006"
		],
		[
			"t01_006",
			"t01_006",
			"t01_006",
			"t01_006",
			"t01_006",
			"t01_006",
			"t01_006",
			"t01_006",
			"t01_006",
			"t01_006",
			"t01_006",
			"t01_006",
			"t01_006",
			"t01_006",
			"t01_006",
			"t01_006",
			"t01_006",
			"t01_006",
			"t01_003",
			"t01_000",
			"t01_000",
			"t01_000",
			"t01_002",
			"t01_002",
			"t01_002",
			"t01_000",
			"t01_000",
			"t01_000",
			"t01_006",
			"t01_006",
			"t01_006",
			"t01_006",
			"t01_006",
			"t01_006",
			"t01_006",
			"t01_006",
			"t01_003",
			"t01_000",
			"t01_002",
			"t01_002",
			"t01_002",
			"t01_002",
			"t01_002",
			"t01_000",
			"t01_006",
			"t01_006",
			"t01_006",
			"t01_006"
		],
		[
			"t01_006",
			"t01_006",
			"t01_006",
			"t01_006",
			"t01_006",
			"t01_006",
			"t01_006",
			"t01_006",
			"t01_006",
			"t01_006",
			"t01_006",
			"t01_006",
			"t01_006",
			"t01_006",
			"t01_006",
			"t01_006",
			"t01_006",
			"t01_006",
			"t01_003",
			"t01_000",
			"t01_000",
			"t01_000",
			"t01_002",
			"t01_002",
			"t01_002",
			"t01_000",
			"t01_000",
			"t01_000",
			"t01_006",
			"t01_006",
			"t01_006",
			"t01_006",
			"t01_006",
			"t01_006",
			"t01_006",
			"t01_006",
			"t01_003",
			"t01_000",
			"t01_002",
			"t01_002",
			"t01_002",
			"t01_002",
			"t01_006",
			"t01_006",
			"t01_006",
			"t01_006",
			"t01_006",
			"t01_006"
		],
		[
			"t01_006",
			"t01_006",
			"t01_006",
			"t01_006",
			"t01_006",
			"t01_006",
			"t01_006",
			"t01_006",
			"t01_006",
			"t01_006",
			"t01_006",
			"t01_006",
			"t01_006",
			"t01_006",
			"t01_006",
			"t01_006",
			"t01_006",
			"t01_003",
			"t01_000",
			"t01_000",
			"t01_000",
			"t01_000",
			"t01_002",
			"t01_002",
			"t01_002",
			"t01_000",
			"t01_000",
			"t01_000",
			"t01_006",
			"t01_006",
			"t01_006",
			"t01_006",
			"t01_006",
			"t01_006",
			"t01_006",
			"t01_006",
			"t01_003",
			"t01_002",
			"t01_002",
			"t01_002",
			"t01_006",
			"t01_006",
			"t01_006",
			"t01_006",
			"t01_006",
			"t01_006",
			"t01_006",
			"t01_006"
		],
		[
			"t01_006",
			"t01_006",
			"t01_006",
			"t01_006",
			"t01_006",
			"t01_006",
			"t01_006",
			"t01_006",
			"t01_006",
			"t01_006",
			"t01_006",
			"t01_006",
			"t01_006",
			"t01_006",
			"t01_006",
			"t01_006",
			"t01_006",
			"t01_006",
			"t01_003",
			"t01_001",
			"t01_000",
			"t01_000",
			"t01_006",
			"t01_006",
			"t01_003",
			"t01_000",
			"t01_001",
			"t01_000",
			"t01_000",
			"t01_006",
			"t01_006",
			"t01_006",
			"t01_006",
			"t01_006",
			"t01_006",
			"t01_006",
			"t01_003",
			"t01_002",
			"t01_002",
			"t01_002",
			"t01_006",
			"t01_006",
			"t01_006",
			"t01_006",
			"t01_006",
			"t01_006",
			"t01_006",
			"t01_006"
		],
		[
			"t01_006",
			"t01_006",
			"t01_006",
			"t01_006",
			"t01_006",
			"t01_006",
			"t01_006",
			"t01_006",
			"t01_006",
			"t01_006",
			"t01_006",
			"t01_006",
			"t01_006",
			"t01_006",
			"t01_006",
			"t01_006",
			"t01_006",
			"t01_006",
			"t01_006",
			"t01_003",
			"t01_000",
			"t01_006",
			"t01_006",
			"t01_006",
			"t01_003",
			"t01_000",
			"t01_000",
			"t01_000",
			"t01_000",
			"t01_006",
			"t01_006",
			"t01_006",
			"t01_006",
			"t01_006",
			"t01_006",
			"t01_003",
			"t01_000",
			"t01_002",
			"t01_002",
			"t01_002",
			"t01_006",
			"t01_006",
			"t01_006",
			"t01_006",
			"t01_006",
			"t01_006",
			"t01_006",
			"t01_006"
		],
		[
			"t01_006",
			"t01_006",
			"t01_006",
			"t01_006",
			"t01_006",
			"t01_006",
			"t01_006",
			"t01_006",
			"t01_006",
			"t01_006",
			"t01_006",
			"t01_006",
			"t01_006",
			"t01_006",
			"t01_006",
			"t01_006",
			"t01_006",
			"t01_006",
			"t01_006",
			"t01_006",
			"t01_006",
			"t01_006",
			"t01_006",
			"t01_006",
			"t01_003",
			"t01_000",
			"t01_000",
			"t01_000",
			"t01_000",
			"t01_006",
			"t01_006",
			"t01_006",
			"t01_006",
			"t01_006",
			"t01_006",
			"t01_003",
			"t01_000",
			"t01_000",
			"t01_000",
			"t01_000",
			"t01_006",
			"t01_006",
			"t01_006",
			"t01_006",
			"t01_006",
			"t01_006",
			"t01_006",
			"t01_006"
		],
		[
			"t01_006",
			"t01_006",
			"t01_006",
			"t01_006",
			"t01_006",
			"t01_006",
			"t01_006",
			"t01_006",
			"t01_006",
			"t01_006",
			"t01_006",
			"t01_006",
			"t01_006",
			"t01_006",
			"t01_006",
			"t01_006",
			"t01_006",
			"t01_006",
			"t01_006",
			"t01_006",
			"t01_006",
			"t01_006",
			"t01_006",
			"t01_006",
			"t01_006",
			"t01_003",
			"t01_000",
			"t01_000",
			"t01_000",
			"t01_006",
			"t01_006",
			"t01_006",
			"t01_006",
			"t01_006",
			"t01_006",
			"t01_003",
			"t01_002",
			"t01_002",
			"t01_002",
			"t01_002",
			"t01_006",
			"t01_006",
			"t01_006",
			"t01_006",
			"t01_006",
			"t01_006",
			"t01_006",
			"t01_006"
		],
		[
			"t01_006",
			"t01_006",
			"t01_006",
			"t01_006",
			"t01_006",
			"t01_006",
			"t01_006",
			"t01_006",
			"t01_006",
			"t01_006",
			"t01_006",
			"t01_006",
			"t01_006",
			"t01_006",
			"t01_006",
			"t01_006",
			"t01_006",
			"t01_006",
			"t01_006",
			"t01_006",
			"t01_006",
			"t01_006",
			"t01_006",
			"t01_006",
			"t01_006",
			"t01_003",
			"t01_000",
			"t01_000",
			"t01_000",
			"t01_006",
			"t01_006",
			"t01_006",
			"t01_006",
			"t01_006",
			"t01_006",
			"t01_003",
			"t01_002",
			"t01_002",
			"t01_002",
			"t01_006",
			"t01_006",
			"t01_006",
			"t01_006",
			"t01_006",
			"t01_006",
			"t01_006",
			"t01_006",
			"t01_006"
		],
		[
			"t01_006",
			"t01_006",
			"t01_006",
			"t01_006",
			"t01_006",
			"t01_006",
			"t01_006",
			"t01_006",
			"t01_006",
			"t01_006",
			"t01_006",
			"t01_006",
			"t01_006",
			"t01_006",
			"t01_006",
			"t01_006",
			"t01_006",
			"t01_006",
			"t01_006",
			"t01_006",
			"t01_006",
			"t01_006",
			"t01_006",
			"t01_006",
			"t01_006",
			"t01_003",
			"t01_000",
			"t01_000",
			"t01_000",
			"t01_000",
			"t01_006",
			"t01_006",
			"t01_006",
			"t01_006",
			"t01_006",
			"t01_003",
			"t01_002",
			"t01_002",
			"t01_002",
			"t01_006",
			"t01_006",
			"t01_006",
			"t01_006",
			"t01_006",
			"t01_006",
			"t01_006",
			"t01_006",
			"t01_006"
		],
		[
			"t01_006",
			"t01_006",
			"t01_006",
			"t01_006",
			"t01_006",
			"t01_006",
			"t01_006",
			"t01_006",
			"t01_006",
			"t01_006",
			"t01_006",
			"t01_006",
			"t01_006",
			"t01_006",
			"t01_006",
			"t01_006",
			"t01_006",
			"t01_006",
			"t01_006",
			"t01_006",
			"t01_006",
			"t01_006",
			"t01_006",
			"t01_006",
			"t01_006",
			"t01_003",
			"t01_000",
			"t01_000",
			"t01_000",
			"t01_000",
			"t01_000",
			"t01_006",
			"t01_006",
			"t01_006",
			"t01_003",
			"t01_000",
			"t01_000",
			"t01_000",
			"t01_000",
			"t01_006",
			"t01_006",
			"t01_006",
			"t01_006",
			"t01_006",
			"t01_006",
			"t01_006",
			"t01_006",
			"t01_006"
		],
		[
			"t01_006",
			"t01_006",
			"t01_006",
			"t01_006",
			"t01_006",
			"t01_006",
			"t01_006",
			"t01_006",
			"t01_006",
			"t01_006",
			"t01_006",
			"t01_006",
			"t01_006",
			"t01_003",
			"t01_002",
			"t01_006",
			"t01_006",
			"t01_006",
			"t01_006",
			"t01_006",
			"t01_006",
			"t01_006",
			"t01_006",
			"t01_006",
			"t01_006",
			"t01_003",
			"t01_000",
			"t01_000",
			"t01_000",
			"t01_000",
			"t01_000",
			"t01_000",
			"t01_006",
			"t01_006",
			"t01_003",
			"t01_000",
			"t01_000",
			"t01_000",
			"t01_000",
			"t01_006",
			"t01_006",
			"t01_006",
			"t01_006",
			"t01_006",
			"t01_006",
			"t01_006",
			"t01_006",
			"t01_006"
		],
		[
			"t01_006",
			"t01_006",
			"t01_006",
			"t01_006",
			"t01_006",
			"t01_006",
			"t01_006",
			"t01_006",
			"t01_006",
			"t01_006",
			"t01_006",
			"t01_006",
			"t01_003",
			"t01_002",
			"t01_002",
			"t01_002",
			"t01_002",
			"t01_002",
			"t01_000",
			"t01_000",
			"t01_000",
			"t01_000",
			"t01_000",
			"t01_000",
			"t01_001",
			"t01_000",
			"t01_000",
			"t01_000",
			"t01_000",
			"t01_000",
			"t01_000",
			"t01_000",
			"t01_000",
			"t01_006",
			"t01_003",
			"t01_000",
			"t01_000",
			"t01_000",
			"t01_000",
			"t01_006",
			"t01_006",
			"t01_006",
			"t01_006",
			"t01_006",
			"t01_006",
			"t01_006",
			"t01_006",
			"t01_006"
		],
		[
			"t01_006",
			"t01_006",
			"t01_006",
			"t01_006",
			"t01_006",
			"t01_006",
			"t01_006",
			"t01_006",
			"t01_006",
			"t01_006",
			"t01_006",
			"t01_003",
			"t01_002",
			"t01_002",
			"t01_000",
			"t01_002",
			"t01_002",
			"t01_002",
			"t01_000",
			"t01_000",
			"t01_000",
			"t01_000",
			"t01_000",
			"t01_000",
			"t01_000",
			"t01_000",
			"t01_000",
			"t01_000",
			"t01_000",
			"t01_000",
			"t01_000",
			"t01_000",
			"t01_000",
			"t01_006",
			"t01_003",
			"t01_000",
			"t01_000",
			"t01_000",
			"t01_006",
			"t01_006",
			"t01_006",
			"t01_006",
			"t01_006",
			"t01_006",
			"t01_006",
			"t01_006",
			"t01_006",
			"t01_006"
		],
		[
			"t01_006",
			"t01_006",
			"t01_006",
			"t01_006",
			"t01_006",
			"t01_006",
			"t01_006",
			"t01_006",
			"t01_006",
			"t01_006",
			"t01_006",
			"t01_006",
			"t01_003",
			"t01_002",
			"t01_002",
			"t01_002",
			"t01_002",
			"t01_002",
			"t01_000",
			"t01_000",
			"t01_000",
			"t01_000",
			"t01_000",
			"t01_000",
			"t01_000",
			"t01_000",
			"t01_000",
			"t01_000",
			"t01_000",
			"t01_000",
			"t01_000",
			"t01_000",
			"t01_000",
			"t01_006",
			"t01_003",
			"t01_000",
			"t01_000",
			"t01_000",
			"t01_006",
			"t01_006",
			"t01_006",
			"t01_006",
			"t01_006",
			"t01_006",
			"t01_006",
			"t01_006",
			"t01_006",
			"t01_006"
		],
		[
			"t01_006",
			"t01_006",
			"t01_006",
			"t01_006",
			"t01_006",
			"t01_006",
			"t01_006",
			"t01_006",
			"t01_006",
			"t01_006",
			"t01_006",
			"t01_006",
			"t01_006",
			"t01_003",
			"t01_002",
			"t01_006",
			"t01_006",
			"t01_006",
			"t01_006",
			"t01_006",
			"t01_006",
			"t01_006",
			"t01_006",
			"t01_006",
			"t01_006",
			"t01_006",
			"t01_006",
			"t01_006",
			"t01_006",
			"t01_003",
			"t01_002",
			"t01_002",
			"t01_002",
			"t01_002",
			"t01_002",
			"t01_000",
			"t01_001",
			"t01_000",
			"t01_006",
			"t01_006",
			"t01_006",
			"t01_006",
			"t01_006",
			"t01_006",
			"t01_006",
			"t01_006",
			"t01_006",
			"t01_006"
		],
		[
			"t01_006",
			"t01_006",
			"t01_006",
			"t01_006",
			"t01_006",
			"t01_006",
			"t01_006",
			"t01_006",
			"t01_006",
			"t01_006",
			"t01_006",
			"t01_006",
			"t01_006",
			"t01_006",
			"t01_006",
			"t01_006",
			"t01_006",
			"t01_006",
			"t01_006",
			"t01_006",
			"t01_006",
			"t01_006",
			"t01_006",
			"t01_006",
			"t01_006",
			"t01_006",
			"t01_006",
			"t01_006",
			"t01_006",
			"t01_003",
			"t01_002",
			"t01_002",
			"t01_002",
			"t01_002",
			"t01_002",
			"t01_000",
			"t01_000",
			"t01_000",
			"t01_006",
			"t01_006",
			"t01_006",
			"t01_006",
			"t01_006",
			"t01_006",
			"t01_006",
			"t01_006",
			"t01_006",
			"t01_006"
		],
		[
			"t01_006",
			"t01_006",
			"t01_006",
			"t01_006",
			"t01_006",
			"t01_006",
			"t01_006",
			"t01_006",
			"t01_006",
			"t01_006",
			"t01_006",
			"t01_006",
			"t01_006",
			"t01_006",
			"t01_006",
			"t01_006",
			"t01_006",
			"t01_006",
			"t01_006",
			"t01_006",
			"t01_006",
			"t01_006",
			"t01_006",
			"t01_006",
			"t01_006",
			"t01_006",
			"t01_006",
			"t01_006",
			"t01_006",
			"t01_006",
			"t01_003",
			"t01_002",
			"t01_002",
			"t01_002",
			"t01_002",
			"t01_000",
			"t01_000",
			"t01_001",
			"t01_000",
			"t01_006",
			"t01_006",
			"t01_006",
			"t01_006",
			"t01_006",
			"t01_006",
			"t01_006",
			"t01_006",
			"t01_006"
		],
		[
			"t01_006",
			"t01_006",
			"t01_006",
			"t01_006",
			"t01_006",
			"t01_006",
			"t01_006",
			"t01_006",
			"t01_006",
			"t01_006",
			"t01_006",
			"t01_006",
			"t01_006",
			"t01_006",
			"t01_006",
			"t01_006",
			"t01_006",
			"t01_006",
			"t01_006",
			"t01_006",
			"t01_006",
			"t01_006",
			"t01_006",
			"t01_006",
			"t01_006",
			"t01_006",
			"t01_006",
			"t01_006",
			"t01_006",
			"t01_006",
			"t01_006",
			"t01_006",
			"t01_006",
			"t01_006",
			"t01_003",
			"t01_000",
			"t01_000",
			"t01_000",
			"t01_006",
			"t01_006",
			"t01_006",
			"t01_006",
			"t01_006",
			"t01_006",
			"t01_006",
			"t01_006",
			"t01_006",
			"t01_006"
		],
		[
			"t01_006",
			"t01_006",
			"t01_006",
			"t01_006",
			"t01_006",
			"t01_006",
			"t01_006",
			"t01_006",
			"t01_006",
			"t01_006",
			"t01_006",
			"t01_006",
			"t01_006",
			"t01_006",
			"t01_006",
			"t01_006",
			"t01_006",
			"t01_006",
			"t01_006",
			"t01_006",
			"t01_006",
			"t01_006",
			"t01_006",
			"t01_006",
			"t01_006",
			"t01_006",
			"t01_006",
			"t01_006",
			"t01_006",
			"t01_006",
			"t01_006",
			"t01_006",
			"t01_006",
			"t01_006",
			"t01_006",
			"t01_003",
			"t01_001",
			"t01_006",
			"t01_006",
			"t01_006",
			"t01_006",
			"t01_006",
			"t01_006",
			"t01_006",
			"t01_006",
			"t01_006",
			"t01_006",
			"t01_006"
		],
		[
			"t01_006",
			"t01_006",
			"t01_006",
			"t01_006",
			"t01_006",
			"t01_006",
			"t01_006",
			"t01_006",
			"t01_006",
			"t01_006",
			"t01_006",
			"t01_006",
			"t01_006",
			"t01_006",
			"t01_006",
			"t01_006",
			"t01_006",
			"t01_006",
			"t01_006",
			"t01_006",
			"t01_006",
			"t01_006",
			"t01_006",
			"t01_006",
			"t01_006",
			"t01_006",
			"t01_006",
			"t01_006",
			"t01_006",
			"t01_006",
			"t01_006",
			"t01_006",
			"t01_006",
			"t01_006",
			"t01_006",
			"t01_006",
			"t01_006",
			"t01_006",
			"t01_006",
			"t01_006",
			"t01_006",
			"t01_006",
			"t01_006",
			"t01_006",
			"t01_006",
			"t01_006",
			"t01_006",
			"t01_006"
		],
		[
			"t01_006",
			"t01_006",
			"t01_006",
			"t01_006",
			"t01_006",
			"t01_006",
			"t01_006",
			"t01_006",
			"t01_006",
			"t01_006",
			"t01_006",
			"t01_006",
			"t01_006",
			"t01_006",
			"t01_006",
			"t01_006",
			"t01_006",
			"t01_006",
			"t01_006",
			"t01_006",
			"t01_006",
			"t01_006",
			"t01_006",
			"t01_006",
			"t01_006",
			"t01_006",
			"t01_006",
			"t01_006",
			"t01_006",
			"t01_006",
			"t01_006",
			"t01_006",
			"t01_006",
			"t01_006",
			"t01_006",
			"t01_006",
			"t01_006",
			"t01_006",
			"t01_006",
			"t01_006",
			"t01_006",
			"t01_006",
			"t01_006",
			"t01_006",
			"t01_006",
			"t01_006",
			"t01_006",
			"t01_006"
		],
		[
			"t01_006",
			"t01_006",
			"t01_006",
			"t01_006",
			"t01_006",
			"t01_006",
			"t01_006",
			"t01_006",
			"t01_006",
			"t01_006",
			"t01_006",
			"t01_006",
			"t01_006",
			"t01_006",
			"t01_006",
			"t01_006",
			"t01_006",
			"t01_006",
			"t01_006",
			"t01_006",
			"t01_006",
			"t01_006",
			"t01_006",
			"t01_006",
			"t01_006",
			"t01_006",
			"t01_006",
			"t01_006",
			"t01_006",
			"t01_006",
			"t01_006",
			"t01_006",
			"t01_006",
			"t01_006",
			"t01_006",
			"t01_006",
			"t01_006",
			"t01_006",
			"t01_006",
			"t01_006",
			"t01_006",
			"t01_006",
			"t01_006",
			"t01_006",
			"t01_006",
			"t01_006",
			"t01_006",
			"t01_006"
		],
		[
			"t01_006",
			"t01_006",
			"t01_006",
			"t01_006",
			"t01_006",
			"t01_006",
			"t01_006",
			"t01_006",
			"t01_006",
			"t01_006",
			"t01_006",
			"t01_006",
			"t01_006",
			"t01_006",
			"t01_006",
			"t01_006",
			"t01_006",
			"t01_006",
			"t01_006",
			"t01_006",
			"t01_006",
			"t01_006",
			"t01_006",
			"t01_006",
			"t01_006",
			"t01_006",
			"t01_006",
			"t01_006",
			"t01_006",
			"t01_006",
			"t01_006",
			"t01_006",
			"t01_006",
			"t01_006",
			"t01_006",
			"t01_006",
			"t01_006",
			"t01_006",
			"t01_006",
			"t01_006",
			"t01_006",
			"t01_006",
			"t01_006",
			"t01_006",
			"t01_006",
			"t01_006",
			"t01_006",
			"t01_006"
		]
	],
	"map_weather": [],
	"map_info": {
		"map_battleback": "battle_bg_fungal_cave",
		"map_name": "Everchange Cave - Floor 1",
		"map_generated": true,
		"map_failsafe_pos": {
			"x": 37,
			"y": 14
		}
	}
}